metricslib/__init__.py
metricslib/clients.py
metricslib/config.py
metricslib/decorators.py
metricslib/exceptions.py
metricslib/listeners.py
metricslib/metrics.py
metricslib/utils.py
metricslib-0.3.0.dist-info/LICENSE
metricslib-0.3.0.dist-info/METADATA
metricslib-0.3.0.dist-info/WHEEL
metricslib-0.3.0.dist-info/top_level.txt
metricslib-0.3.0.dist-info/zip-safe
metricslib-0.3.0.dist-info/RECORD
